datawire_quark-1.0.452.dist-info/DESCRIPTION.rst
datawire_quark-1.0.452.dist-info/METADATA
datawire_quark-1.0.452.dist-info/RECORD
datawire_quark-1.0.452.dist-info/WHEEL
datawire_quark-1.0.452.dist-info/entry_points.txt
datawire_quark-1.0.452.dist-info/metadata.json
datawire_quark-1.0.452.dist-info/top_level.txt
quarkc/__init__.py
quarkc/_metadata.py
quarkc/ast.py
quarkc/backend.py
quarkc/coder.py
quarkc/command.py
quarkc/compiler.py
quarkc/constants.py
quarkc/dispatch.py
quarkc/docmaker.py
quarkc/docrenderer.py
quarkc/environment.py
quarkc/errors.py
quarkc/exceptions.py
quarkc/grammar.py
quarkc/helpers.py
quarkc/java.py
quarkc/javascript.py
quarkc/messages.py
quarkc/parser.py
quarkc/pprinter.py
quarkc/python.py
quarkc/reflection.py
quarkc/ruby.py
quarkc/shell.py
quarkc/test_versioning.py
quarkc/versioning.py
quarkc/apidoc/apidoc.css
quarkc/apidoc/base.html
quarkc/apidoc/index.html
quarkc/apidoc/macros.html
quarkc/lib/concurrent.q
quarkc/lib/datawire-quark-core.rb
quarkc/lib/http.q
quarkc/lib/io.q
quarkc/lib/json.q
quarkc/lib/logging.q
quarkc/lib/mock.q
quarkc/lib/os.q
quarkc/lib/primitives.q
quarkc/lib/promise.q
quarkc/lib/quark.q
quarkc/lib/quark_node_runtime.js
quarkc/lib/quark_runtime.js
quarkc/lib/quark_runtime.py
quarkc/lib/quark_runtime_logging.py
quarkc/lib/quark_threaded_runtime.py
quarkc/lib/quark_ws4py_fixup.py
quarkc/lib/reflect.q
quarkc/lib/service.q
quarkc/lib/spi.q
quarkc/lib/spi_api.q
quarkc/lib/spi_api_tracing.q
quarkc/lib/testing.q
quarkc/lib/url.q
quarkc/lib/ws.q
quarkc/lib/io/datawire/quark/netty/DatawireNettyHttpContainer.java
quarkc/lib/io/datawire/quark/netty/IncomingRequest.java
quarkc/lib/io/datawire/quark/netty/QuarkNettyClientWebsocket.java
quarkc/lib/io/datawire/quark/netty/QuarkNettyHttpHandler.java
quarkc/lib/io/datawire/quark/netty/QuarkNettyRuntime.java
quarkc/lib/io/datawire/quark/netty/QuarkNettyServerWebsocket.java
quarkc/lib/io/datawire/quark/netty/QuarkWebSocket.java
quarkc/lib/io/datawire/quark/netty/Response.java
quarkc/lib/io/datawire/quark/runtime/AbstractDatawireRuntime.java
quarkc/lib/io/datawire/quark/runtime/AbstractHTTPHandler.java
quarkc/lib/io/datawire/quark/runtime/AbstractWSHandler.java
quarkc/lib/io/datawire/quark/runtime/Buffer.java
