Metadata-Version: 2.0
Name: datawire-quark
Version: 1.0.452
Summary: Quark: an IDL for high level (micro)service interfaces
Home-page: http://datawire.github.io/quark/
Author: datawire.io
Author-email: hello@datawire.io
License: Apache License, Version 2.0
Keywords: IDL,service,microservice,RPC,async
Platform: UNKNOWN
Classifier: Development Status :: 3 - Alpha
Classifier: Environment :: Console
Classifier: Intended Audience :: Developers
Classifier: License :: OSI Approved :: Apache Software License
Classifier: Operating System :: MacOS
Classifier: Operating System :: OS Independent
Classifier: Operating System :: POSIX
Classifier: Programming Language :: Java
Classifier: Programming Language :: JavaScript
Classifier: Programming Language :: Python
Classifier: Topic :: Software Development
Requires-Dist: docopt (==0.6.2)
Requires-Dist: parsimonious (==0.6.2)
Requires-Dist: sphinx (>=1.3.1)
Requires-Dist: setuptools (>=18)
Requires-Dist: pip (>=8)
Requires-Dist: wheel
Requires-Dist: markdown
Requires-Dist: Jinja2 (>=2.8)
